fastsecforge/__init__.py
fastsecforge/cli.py
fastsecforge/config.py
fastsecforge/database.py
fastsecforge/main.py
fastsecforge/core/__init__.py
fastsecforge/core/security.py
fastsecforge/models/__init__.py
fastsecforge/models/user.py
fastsecforge/routers/__init__.py
fastsecforge/routers/auth.py
fastsecforge/routers/users.py
fastsecforge/schemas/__init__.py
fastsecforge/schemas/user.py
fastsecforge/templates/project_template/.env
fastsecforge/templates/project_template/requirements.txt
fastsecforge/templates/project_template/src/PROJECT_NAME/__init__.py
fastsecforge/templates/project_template/src/PROJECT_NAME/config.py
fastsecforge/templates/project_template/src/PROJECT_NAME/database.py
fastsecforge/templates/project_template/src/PROJECT_NAME/main.py
fastsecforge/templates/project_template/src/PROJECT_NAME/core/__init__.py
fastsecforge/templates/project_template/src/PROJECT_NAME/core/security.py
fastsecforge/templates/project_template/src/PROJECT_NAME/models/__init__.py
fastsecforge/templates/project_template/src/PROJECT_NAME/models/user.py
fastsecforge/templates/project_template/src/PROJECT_NAME/routers/__init__.py
fastsecforge/templates/project_template/src/PROJECT_NAME/routers/auth.py
fastsecforge/templates/project_template/src/PROJECT_NAME/routers/users.py
fastsecforge/templates/project_template/src/PROJECT_NAME/schemas/__init__.py
fastsecforge/templates/project_template/src/PROJECT_NAME/schemas/user.py
fastsecforge-0.1.4.dist-info/LICENSE
fastsecforge-0.1.4.dist-info/METADATA
fastsecforge-0.1.4.dist-info/WHEEL
fastsecforge-0.1.4.dist-info/entry_points.txt
fastsecforge-0.1.4.dist-info/top_level.txt
fastsecforge-0.1.4.dist-info/RECORD
