Metadata-Version: 2.1
Name: fastsecforge
Version: 0.1.4
License-File: LICENSE
Requires-Dist: fastapi
Requires-Dist: uvicorn
Requires-Dist: python-dotenv
Requires-Dist: sqlalchemy
Requires-Dist: pydantic>=2.0.0
Requires-Dist: pydantic-settings>=2.0.0
Requires-Dist: passlib[bcrypt]
Requires-Dist: python-jose[cryptography]
Requires-Dist: motor
Requires-Dist: typer
Requires-Dist: python-multipart
Requires-Dist: cors
Requires-Dist: psycopg2-binary
